plot_model/__init__.py
plot_model/plot_model.py
plot_model-0.20.dist-info/LICENSE
plot_model-0.20.dist-info/METADATA
plot_model-0.20.dist-info/WHEEL
plot_model-0.20.dist-info/top_level.txt
plot_model-0.20.dist-info/RECORD
