Metadata-Version: 2.1
Name: plot-model
Version: 0.20
Summary: plot model
Home-page: https://github.com/Qinbf/plot_model
Author: QinBingFeng
Author-email: 114479602@qq.com
License: UNKNOWN
Platform: UNKNOWN
